AUTHORS.rst
CONTRIBUTING.rst
HISTORY.rst
LICENSE
MANIFEST.in
README.rst
setup.cfg
setup.py
docs/Makefile
docs/authors.rst
docs/conf.py
docs/contributing.rst
docs/history.rst
docs/index.rst
docs/installation.rst
docs/make.bat
docs/modules.rst
docs/readme.rst
docs/usage.rst
docs/html/_images/0.0001.jpg
docs/html/_images/0.00011.jpg
docs/html/_images/0.00012.jpg
docs/html/_images/0.001.jpg
docs/html/_images/0.0011.jpg
docs/html/_images/0.0012.jpg
docs/html/_images/0.01.jpg
docs/html/_images/0.011.jpg
docs/html/_images/0.012.jpg
docs/html/_images/1e-05.jpg
docs/html/_images/1e-051.jpg
docs/html/_images/1e-052.jpg
docs/html/_images/building2_block2_conv2_0.01_style2.png
docs/html/_images/me_pasta.jpg
docs/html/_images/result.jpg
docs/html/_images/result10.jpg
docs/html/_static/ajax-loader.gif
docs/html/_static/comment-bright.png
docs/html/_static/comment-close.png
docs/html/_static/comment.png
docs/html/_static/down-pressed.png
docs/html/_static/down.png
docs/html/_static/file.png
docs/html/_static/minus.png
docs/html/_static/plus.png
docs/html/_static/up-pressed.png
docs/html/_static/up.png
docs/images/cropped_others.png
docs/images/cropped_result.png
docs/images/cropped_results.png
docs/images/result.jpg
docs/images/1/0.0001.jpg
docs/images/1/0.001.jpg
docs/images/1/0.01.jpg
docs/images/1/1e-05.jpg
docs/images/3/0.0001.jpg
docs/images/3/0.001.jpg
docs/images/3/0.01.jpg
docs/images/3/1e-05.jpg
docs/images/6/0.0001.jpg
docs/images/6/0.001.jpg
docs/images/6/0.01.jpg
docs/images/6/1e-05.jpg
pastafy/__init__.py
pastafy/cli.py
pastafy/pastafy.py
pastafy.egg-info/PKG-INFO
pastafy.egg-info/SOURCES.txt
pastafy.egg-info/dependency_links.txt
pastafy.egg-info/entry_points.txt
pastafy.egg-info/not-zip-safe
pastafy.egg-info/top_level.txt
tests/__init__.py
tests/test_pastafy.py