Metadata-Version: 1.2
Name: pastafy
Version: 0.1.0
Summary: Pastafy anyone.
Home-page: https://github.com/sfp932705/pastafy
Author: Sergio Frayle Pérez
Author-email: sfp932705@gmail.com
License: GNU General Public License v3
Keywords: pastafy
Platform: UNKNOWN
Classifier: Development Status :: 2 - Pre-Alpha
Classifier: Intended Audience :: Developers
Classifier: License :: OSI Approved :: GNU General Public License v3 (GPLv3)
Classifier: Natural Language :: English
Classifier: Programming Language :: Python :: 3
Classifier: Programming Language :: Python :: 3.5
Classifier: Programming Language :: Python :: 3.6
Classifier: Programming Language :: Python :: 3.7
Classifier: Programming Language :: Python :: 3.8
Requires-Python: >=3.5
